[
    {
        "utc_hours": 16.500,
        "x_km": 18122.9,
        "y_km": 38080.0,
        "z_km": 828.5,
        "vx": 0.00216,
        "vy": -0.00107,
        "vz": 0.06390
    },
    {
        "utc_hours": 16.750,
        "x_km": 18124.8,
        "y_km": 38079.0,
        "z_km": 884.2,
        "vx": 0.00212,
        "vy": -0.00114,
        "vz": 0.05980
    },
    {
        "utc_hours": 16.917,
        "x_km": 18126.1,
        "y_km": 38078.3,
        "z_km": 919.2,
        "vx": 0.00209,
        "vy": -0.00118,
        "vz": 0.05693
    },
    {
        "utc_hours": 17.083,
        "x_km": 18127.3,
        "y_km": 38077.6,
        "z_km": 952.5,
        "vx": 0.00206,
        "vy": -0.00120,
        "vz": 0.05395
    },
    {
        "utc_hours": 18.417,
        "x_km": 18136.7,
        "y_km": 38071.8,
        "z_km": 1148.5,
        "vx": 0.00188,
        "vy": -0.00117,
        "vz": 0.02690
    },
    {
        "utc_hours": 19.667,
        "x_km": 18145.1,
        "y_km": 38067.0,
        "z_km": 1206.3,
        "vx": 0.00189,
        "vy": -0.00092,
        "vz": -0.00148
    },
    {
        "utc_hours": 20.667,
        "x_km": 18152.1,
        "y_km": 38064.0,
        "z_km": 1159.7,
        "vx": 0.00200,
        "vy": -0.00077,
        "vz": -0.02422
    },
    {
        "utc_hours": 21.667,
        "x_km": 18159.5,
        "y_km": 38061.3,
        "z_km": 1033.8,
        "vx": 0.00212,
        "vy": -0.00076,
        "vz": -0.04531
    },
    {
        "utc_hours": 22.667,
        "x_km": 18167.2,
        "y_km": 38058.3,
        "z_km": 837.2,
        "vx": 0.00211,
        "vy": -0.00096,
        "vz": -0.06331
    },
    {
        "utc_hours": 24.167,
        "x_km": 18177.5,
        "y_km": 38051.7,
        "z_km": 440.0,
        "vx": 0.00160,
        "vy": -0.00151,
        "vz": -0.08188
    },
    {
        "utc_hours": 24.333,
        "x_km": 18178.4,
        "y_km": 38050.8,
        "z_km": 390.5,
        "vx": 0.00150,
        "vy": -0.00158,
        "vz": -0.08321
    }
]